Metadata-Version: 1.0
Name: distib-hawa
Version: 0.1
Summary: Gaussian distributions
Home-page: UNKNOWN
Author: Hawa Desai
Author-email: techknowledge.cal@gmail.com
License: UNKNOWN
Platform: UNKNOWN
